gittielabs_fastapi_auth/__init__.py
gittielabs_fastapi_auth/jwt_admin_context.py
gittielabs_fastapi_auth/models.py
gittielabs_fastapi_auth/organization_context.py
gittielabs_fastapi_auth/supabase_auth.py
gittielabs_nextjs_fastapi_auth-0.1.0.dist-info/METADATA
gittielabs_nextjs_fastapi_auth-0.1.0.dist-info/WHEEL
gittielabs_nextjs_fastapi_auth-0.1.0.dist-info/top_level.txt
gittielabs_nextjs_fastapi_auth-0.1.0.dist-info/RECORD
