Metadata-Version: 2.4
Name: gittielabs-nextjs-fastapi-auth
Version: 0.1.0
Summary: Authentication and authorization library for Next.js + FastAPI applications with Supabase
Author-email: GittieLabs <hello@gittielabs.com>
License: MIT
Project-URL: Homepage, https://github.com/gittielabs/nextjs-fastapi-auth
Project-URL: Documentation, https://github.com/gittielabs/nextjs-fastapi-auth#readme
Project-URL: Repository, https://github.com/gittielabs/nextjs-fastapi-auth
Project-URL: Issues, https://github.com/gittielabs/nextjs-fastapi-auth/issues
Keywords: authentication,authorization,fastapi,nextjs,supabase,jwt,multi-tenant,rbac
Classifier: Development Status :: 3 - Alpha
Classifier: Intended Audience :: Developers
Classifier: License :: OSI Approved :: MIT License
Classifier: Programming Language :: Python :: 3
Classifier: Programming Language :: Python :: 3.9
Classifier: Programming Language :: Python :: 3.10
Classifier: Programming Language :: Python :: 3.11
Classifier: Programming Language :: Python :: 3.12
Classifier: Framework :: FastAPI
Classifier: Topic :: Software Development :: Libraries :: Python Modules
Classifier: Topic :: Internet :: WWW/HTTP :: Session
Requires-Python: >=3.9
Requires-Dist: fastapi>=0.100.0
Requires-Dist: pydantic>=2.0.0
Requires-Dist: pyjwt>=2.8.0
Requires-Dist: supabase>=2.0.0
Requires-Dist: loguru>=0.7.0
Provides-Extra: dev
Requires-Dist: pytest>=7.0.0; extra == "dev"
Requires-Dist: pytest-asyncio>=0.21.0; extra == "dev"
Requires-Dist: httpx>=0.24.0; extra == "dev"
Requires-Dist: black>=23.0.0; extra == "dev"
Requires-Dist: ruff>=0.1.0; extra == "dev"
Requires-Dist: mypy>=1.0.0; extra == "dev"
